{
  "eligible": false,
  "eligibility_reasons": [
    "GCSE English Language below the pass grade (4)",
    "Fewer than the required number of GCSE passes (5 at grade 4 or above)"
  ],
  "recommendations": [
    {
      "subject": "further_maths",
      "rating": "red",
      "reason": "GCSE English Language below the pass grade (4)"
    },
    {
      "subject": "design_technology",
      "rating": "red",
      "reason": "GCSE English Language below the pass grade (4)"
    },
    {
      "subject": "spanish",
      "rating": "red",
      "reason": "GCSE English Language below the pass grade (4)"
    },
    {
      "subject": "law",
      "rating": "red",
      "reason": "GCSE English Language below the pass grade (4)"
    },
    {
      "subject": "religious_studies",
      "rating": "red",
      "reason": "GCSE English Language below the pass grade (4)"
    },
    {
      "subject": "politics",
      "rating": "red",
      "reason": "GCSE English Language below the pass grade (4)"
    },
    {
      "subject": "maths",
      "rating": "red",
      "reason": "GCSE English Language below the pass grade (4)"
    },
    {
      "subject": "geography",
      "rating": "red",
      "reason": "GCSE English Language below the pass grade (4)"
    },
    {
      "subject": "physics",
      "rating": "red",
      "reason": "GCSE English Language below the pass grade (4)"
    },
    {
      "subject": "psychology",
      "rating": "red",
      "reason": "GCSE English Language below the pass grade (4)"
    },
    {
      "subject": "chemistry",
      "rating": "red",
      "reason": "GCSE English Language below the pass grade (4)"
    },
    {
      "subject": "economics",
      "rating": "red",
      "reason": "GCSE English Language below the pass grade (4)"
    },
    {
      "subject": "biology",
      "rating": "red",
      "reason": "GCSE English Language below the pass grade (4)"
    },
    {
      "subject": "computer_studies",
      "rating": "red",
      "reason": "GCSE English Language below the pass grade (4)"
    },
    {
      "subject": "english_literature",
      "rating": "red",
      "reason": "GCSE English Language below the pass grade (4)"
    },
    {
      "subject": "english_language",
      "rating": "red",
      "reason": "GCSE English Language below the pass grade (4)"
    },
    {
      "subject": "history",
      "rating": "red",
      "reason": "GCSE English Language below the pass grade (4)"
    },
    {
      "subject": "french",
      "rating": "red",
      "reason": "GCSE English Language below the pass grade (4)"
    },
    {
      "subject": "art",
      "rating": "red",
      "reason": "GCSE English Language below the pass grade (4)"
    },
    {
      "subject": "german",
      "rating": "red",
      "reason": "GCSE English Language below the pass grade (4)"
    },
    {
      "subject": "music",
      "rating": "red",
      "reason": "GCSE English Language below the pass grade (4)"
    },
    {
      "subject": "physical_education",
      "rating": "red",
      "reason": "GCSE English Language below the pass grade (4)"
    },
    {
      "subject": "business_studies",
      "rating": "red",
      "reason": "GCSE English Language below the pass grade (4)"
    },
    {
      "subject": "sociology",
      "rating": "red",
      "reason": "GCSE English Language below the pass grade (4)"
    },
    {
      "subject": "media_studies",
      "rating": "red",
      "reason": "GCSE English Language below the pass grade (4)"
    },
    {
      "subject": "drama",
      "rating": "red",
      "reason": "GCSE English Language below the pass grade (4)"
    }
  ],
  "summary": {
    "green_count": 0,
    "amber_count": 0,
    "projected_tariff": 0
  },
  "adjustments": []
}
